clamps/__init__.py
clamps/bin/debug.py
clamps/js.py
clamps-0.1.3.dist-info/LICENSE
clamps-0.1.3.dist-info/WHEEL
clamps-0.1.3.dist-info/METADATA
clamps-0.1.3.dist-info/RECORD
